odoo/addons/account_credit_control_attach_invoice/README.rst
odoo/addons/account_credit_control_attach_invoice/__init__.py
odoo/addons/account_credit_control_attach_invoice/__manifest__.py
odoo/addons/account_credit_control_attach_invoice/i18n/account_credit_control_attach_invoice.pot
odoo/addons/account_credit_control_attach_invoice/i18n/it.po
odoo/addons/account_credit_control_attach_invoice/models/__init__.py
odoo/addons/account_credit_control_attach_invoice/models/report.py
odoo/addons/account_credit_control_attach_invoice/models/res_company.py
odoo/addons/account_credit_control_attach_invoice/models/res_config_settings.py
odoo/addons/account_credit_control_attach_invoice/readme/CONFIGURE.md
odoo/addons/account_credit_control_attach_invoice/readme/CONTRIBUTORS.md
odoo/addons/account_credit_control_attach_invoice/readme/CREDITS.md
odoo/addons/account_credit_control_attach_invoice/readme/DESCRIPTION.md
odoo/addons/account_credit_control_attach_invoice/readme/USAGE.md
odoo/addons/account_credit_control_attach_invoice/static/description/icon.png
odoo/addons/account_credit_control_attach_invoice/static/description/index.html
odoo/addons/account_credit_control_attach_invoice/tests/__init__.py
odoo/addons/account_credit_control_attach_invoice/tests/test_ir_action_report.py
odoo/addons/account_credit_control_attach_invoice/views/res_config_settings.xml
odoo_addon_account_credit_control_attach_invoice-18.0.1.0.0.9.dist-info/METADATA
odoo_addon_account_credit_control_attach_invoice-18.0.1.0.0.9.dist-info/WHEEL
odoo_addon_account_credit_control_attach_invoice-18.0.1.0.0.9.dist-info/top_level.txt
odoo_addon_account_credit_control_attach_invoice-18.0.1.0.0.9.dist-info/RECORD
