Metadata-Version: 2.1
Name: odoo-addon-account_credit_control_attach_invoice
Version: 18.0.1.0.0.9
Requires-Python: >=3.10
Requires-Dist: odoo-addon-account_credit_control==18.0.*
Requires-Dist: odoo==18.0.*
Summary: Extend account credit control to print credit control summary with invoices
Home-page: https://github.com/OCA/credit-control
License: AGPL-3
Author: Camptocamp,Odoo Community Association (OCA)
Author-email: support@odoo-community.org
Classifier: Programming Language :: Python
Classifier: Framework :: Odoo
Classifier: Framework :: Odoo :: 18.0
Classifier: License :: OSI Approved :: GNU Affero General Public License v3
